eve_echoes/__init__.py
eve_echoes/loot_distribution/__init__.py
eve_echoes/loot_distribution/distribute.py
eve_echoes-0.1.0.dist-info/LICENSE
eve_echoes-0.1.0.dist-info/METADATA
eve_echoes-0.1.0.dist-info/WHEEL
eve_echoes-0.1.0.dist-info/top_level.txt
eve_echoes-0.1.0.dist-info/RECORD
