Metadata-Version: 2.1
Name: eve-echoes
Version: 0.1.0
Summary: UNKNOWN
Home-page: UNKNOWN
Author: Curtis Mason
Author-email: cumason@bu.edu
License: UNKNOWN
Platform: UNKNOWN
Classifier: Intended Audience :: Information Technology
Classifier: Intended Audience :: System Administrators
Classifier: Operating System :: POSIX :: Linux
Classifier: Programming Language :: Python :: 3.8
Requires-Dist: numpy (<2.0,>1.19)
